crisscross/README.md
crisscross/__init__.py
crisscross/cli_functions/__init__.py
crisscross/cli_functions/handle_evolution.py
crisscross/cli_functions/plate_resuspension.py
crisscross/cli_functions/working_stock_creation.py
crisscross/core_functions/__init__.py
crisscross/core_functions/handle_link_manager.py
crisscross/core_functions/megastructure_composition.py
crisscross/core_functions/megastructures.py
crisscross/core_functions/plate_handling.py
crisscross/core_functions/slat_design.py
crisscross/core_functions/slats.py
crisscross/core_functions/stepwise_plots.py
crisscross/dna_source_plates/assembly_plates/P3250_SW_antihandles.xlsx
crisscross/dna_source_plates/assembly_plates/P3251_CW_antihandles.xlsx
crisscross/dna_source_plates/assembly_plates/P3252_SW_antihandles.xlsx
crisscross/dna_source_plates/assembly_plates/P3533_SW_handles.xlsx
crisscross/dna_source_plates/assembly_plates/P3534_SW_handles.xlsx
crisscross/dna_source_plates/assembly_plates/P3535_SW_handles.xlsx
crisscross/dna_source_plates/assembly_plates/P3536_MA_h2_antihandles.xlsx
crisscross/dna_source_plates/assembly_plates/P3537_MA_h2_antihandles.xlsx
crisscross/dna_source_plates/assembly_plates/P3538_MA_h2_antihandles.xlsx
crisscross/dna_source_plates/assembly_plates/P3601_MA_H5_handles_S1A.xlsx
crisscross/dna_source_plates/assembly_plates/P3602_MA_H5_handles_S1B.xlsx
crisscross/dna_source_plates/assembly_plates/P3603_MA_H5_handles_S1C.xlsx
crisscross/dna_source_plates/assembly_plates/P3604_MA_H2_antihandles_S1A.xlsx
crisscross/dna_source_plates/assembly_plates/P3605_MA_H2_antihandles_S1B.xlsx
crisscross/dna_source_plates/assembly_plates/P3606_MA_H2_antihandles_S1C.xlsx
crisscross/dna_source_plates/assembly_plates/P3649_MA_H5_handles_S1A.xlsx
crisscross/dna_source_plates/assembly_plates/P3650_MA_H5_handles_S1B.xlsx
crisscross/dna_source_plates/assembly_plates/P3651_MA_H5_handles_S1C.xlsx
crisscross/dna_source_plates/assembly_plates/P3652_MA_H5_handles_S2A.xlsx
crisscross_kit-1.2.2.dist-info/METADATA
crisscross_kit-1.2.2.dist-info/WHEEL
crisscross_kit-1.2.2.dist-info/entry_points.txt
crisscross_kit-1.2.2.dist-info/top_level.txt
crisscross_kit-1.2.2.dist-info/RECORD
