Metadata-Version: 2.4
Name: crisscross-kit
Version: 1.2.2
Summary: Unified CAD and scripting packages for megastructure design, handle library generation and visualization.
Author: Matthew Aquilina, Florian Katzmeier, Siyuan Stella Wang, Corey Becker, Yichen Zhao
Project-URL: Homepage, https://github.com/mattaq31/Hash-CAD
Classifier: Programming Language :: Python :: 3
Classifier: License :: OSI Approved :: MIT License
Classifier: Operating System :: OS Independent
Requires-Python: >=3.10
Requires-Dist: pandas>=2.3
Requires-Dist: numpy>=2.2
Requires-Dist: seaborn>=0.13
Requires-Dist: matplotlib>=3.10
Requires-Dist: openpyxl>=3.1
Requires-Dist: xlsxwriter>=3.2
Requires-Dist: tqdm>=4.67
Requires-Dist: click>=8.2
Requires-Dist: colorama>=0.4.6
Requires-Dist: rich-click>=1.8
Requires-Dist: toml>=0.10
Provides-Extra: 3d
Requires-Dist: pyvista; extra == "3d"
Requires-Dist: imageio; extra == "3d"
Requires-Dist: imageio-ffmpeg; extra == "3d"
Provides-Extra: blender
Requires-Dist: bpy==4.2.0; extra == "blender"
